tests/__init__.py
tests/conftest.py
tests/test_random_experiments.py
tests/test_trexselector/__init__.py
tests/test_trexselector/test_add_dummies.py
tests/test_trexselector/test_fdp.py
tests/test_trexselector/test_tpp.py
tests/test_trexselector/test_trex.py
trexselector/FDP.py
trexselector/TPP.py
trexselector/__init__.py
trexselector/add_dummies.py
trexselector/add_dummies_GVS.py
trexselector/fdp_hat.py
trexselector/gauss_data.py
trexselector/lm_dummy.py
trexselector/phi_prime_fun.py
trexselector/random_experiments.py
trexselector/screen_trex.py
trexselector/select_var_fun.py
trexselector/select_var_fun_DA_BT.py
trexselector/trex.py
trexselector-0.6.18.dist-info/LICENSE
trexselector-0.6.18.dist-info/METADATA
trexselector-0.6.18.dist-info/WHEEL
trexselector-0.6.18.dist-info/top_level.txt
trexselector-0.6.18.dist-info/RECORD
