Metadata-Version: 2.1
Name: trexselector
Version: 0.6.18
Summary: T-Rex Selector: High-Dimensional Variable Selection & FDR Control
Home-page: https://github.com/ArnauVilella/TRexSelector-python
Author: Python port by Arnau Vilella
Author-email: avp@connect.ust.hk
Classifier: Programming Language :: Python :: 3
Classifier: License :: OSI Approved :: GNU General Public License v3 (GPLv3)
Classifier: Operating System :: OS Independent
Requires-Python: >=3.8
License-File: LICENSE
Requires-Dist: numpy
Requires-Dist: scipy
Requires-Dist: scikit-learn
Requires-Dist: tlars
Requires-Dist: joblib
Requires-Dist: matplotlib
Requires-Dist: pandas
